{"title":"Reading April 9th, 2017","week":"April 9th, 2017","articles":[{"title":"Lithium-Ion Battery Inventor Introduces New Technology for Fast-Charging, Noncombustible Batteries","date_liked":"April 9, 2017 at 07:23PM","description":"AUSTIN, Texas — A team of engineers led by 94-year-old John Goodenough, professor in the Cockrell School of Engineering at The University of Texas at Austin and…","url":"https://news.utexas.edu/2017/02/28/goodenough-introduces-new-battery-technology","notes":"","":""}]}